dash_material_ui/AppBar.py
dash_material_ui/Box.py
dash_material_ui/Button.py
dash_material_ui/ButtonGroup.py
dash_material_ui/Checkbox.py
dash_material_ui/Container.py
dash_material_ui/Divider.py
dash_material_ui/Drawer.py
dash_material_ui/FormControl.py
dash_material_ui/FormControlLabel.py
dash_material_ui/FormLabel.py
dash_material_ui/Icon.py
dash_material_ui/IconButton.py
dash_material_ui/InputBase.py
dash_material_ui/Link.py
dash_material_ui/List.py
dash_material_ui/ListItem.py
dash_material_ui/PhotoCamera.py
dash_material_ui/Radio.py
dash_material_ui/Switch.py
dash_material_ui/TextField.py
dash_material_ui/Typography.py
dash_material_ui/__init__.py
dash_material_ui/_imports_.py
dash_material_ui/dash_material_ui.min.js
dash_material_ui/dash_material_ui.min.js.map
dash_material_ui/metadata.json
dash_material_ui/package-info.json
dash_material_ui-0.1.2.dist-info/LICENSE
dash_material_ui-0.1.2.dist-info/METADATA
dash_material_ui-0.1.2.dist-info/WHEEL
dash_material_ui-0.1.2.dist-info/top_level.txt
dash_material_ui-0.1.2.dist-info/RECORD
