Metadata-Version: 2.1
Name: dash-material-ui
Version: 0.1.2
Summary: Material UI components for Dash
Home-page: UNKNOWN
Author: Hugo Paquet <paquet.hugo@gmail.com>
Author-email: UNKNOWN
License: MIT
Platform: UNKNOWN
Classifier: Framework :: Dash
